luadoc/__init__.py
luadoc/__main__.py
luadoc/astutils.py
luadoc/core.py
luadoc/emmylua.py
luadoc/luadoc.py
luadoc/model.py
luadoc/parser.py
luadoc/printers.py
luadoc/version.py
luadoc/tests/__init__.py
luadoc/tests/test_emmy_lua_parser.py
luadoc/tests/test_parser.py
luadoc-1.3.1.dist-info/LICENSE
luadoc-1.3.1.dist-info/METADATA
luadoc-1.3.1.dist-info/WHEEL
luadoc-1.3.1.dist-info/entry_points.txt
luadoc-1.3.1.dist-info/top_level.txt
luadoc-1.3.1.dist-info/RECORD
